odoo8_addon_account_payment_unece-8.0.1.0.0-py2.7-nspkg.pth
odoo8_addon_account_payment_unece-8.0.1.0.0.dist-info/top_level.txt
odoo8_addon_account_payment_unece-8.0.1.0.0.dist-info/WHEEL
odoo8_addon_account_payment_unece-8.0.1.0.0.dist-info/RECORD
odoo8_addon_account_payment_unece-8.0.1.0.0.dist-info/metadata.json
odoo8_addon_account_payment_unece-8.0.1.0.0.dist-info/DESCRIPTION.rst
odoo8_addon_account_payment_unece-8.0.1.0.0.dist-info/METADATA
odoo8_addon_account_payment_unece-8.0.1.0.0.dist-info/namespace_packages.txt
odoo_addons/account_payment_unece/__openerp__.py
odoo_addons/account_payment_unece/__init__.py
odoo_addons/account_payment_unece/README.rst
odoo_addons/account_payment_unece/models/payment_mode_type.py
odoo_addons/account_payment_unece/models/unece_code_list.py
odoo_addons/account_payment_unece/models/__init__.py
odoo_addons/account_payment_unece/views/payment_mode_type.xml
odoo_addons/account_payment_unece/data/unece.xml
