Metadata-Version: 2.0
Name: odoo8-addon-account-payment-unece
Version: 8.0.1.0.0
Summary: UNECE nomenclature for the payment mode types
Home-page: http://www.akretion.com
Author: UNKNOWN
Author-email: UNKNOWN
License: AGPL-3
Platform: UNKNOWN
Requires-Dist: odoo (<9.0a,>=8.0a)
Requires-Dist: odoo8-addon-account-banking-payment-export
Requires-Dist: odoo8-addon-base-unece
Classifier: Programming Language :: Python :: 2.7
Classifier: Framework :: Odoo
Classifier: License :: OSI Approved :: GNU Affero General Public License v3
